kathara_lab_checker/__init__.py
kathara_lab_checker/__main__.py
kathara_lab_checker/csv_utils.py
kathara_lab_checker/excel_utils.py
kathara_lab_checker/utils.py
kathara_lab_checker/checks/BridgeCheck.py
kathara_lab_checker/checks/CollisionDomainCheck.py
kathara_lab_checker/checks/CustomCommandCheck.py
kathara_lab_checker/checks/DaemonCheck.py
kathara_lab_checker/checks/DeviceExistenceCheck.py
kathara_lab_checker/checks/IPv6EnabledCheck.py
kathara_lab_checker/checks/InterfaceIPCheck.py
kathara_lab_checker/checks/KernelRouteCheck.py
kathara_lab_checker/checks/ReachabilityCheck.py
kathara_lab_checker/checks/StartupExistenceCheck.py
kathara_lab_checker/checks/SysctlCheck.py
kathara_lab_checker/checks/__init__.py
kathara_lab_checker/checks/applications/__init__.py
kathara_lab_checker/checks/applications/dns/DNSAuthorityCheck.py
kathara_lab_checker/checks/applications/dns/DNSRecordCheck.py
kathara_lab_checker/checks/applications/dns/LocalNSCheck.py
kathara_lab_checker/checks/applications/dns/__init__.py
kathara_lab_checker/checks/applications/http/HTTPCheck.py
kathara_lab_checker/checks/applications/http/__init__.py
kathara_lab_checker/checks/protocols/AnnouncedNetworkCheck.py
kathara_lab_checker/checks/protocols/ProtocolRedistributionCheck.py
kathara_lab_checker/checks/protocols/__init__.py
kathara_lab_checker/checks/protocols/bgp/BGPNeighborCheck.py
kathara_lab_checker/checks/protocols/bgp/BGPRoutesCheck.py
kathara_lab_checker/checks/protocols/bgp/__init__.py
kathara_lab_checker/checks/protocols/evpn/AnnouncedVNICheck.py
kathara_lab_checker/checks/protocols/evpn/EVPNSessionCheck.py
kathara_lab_checker/checks/protocols/evpn/VTEPCheck.py
kathara_lab_checker/checks/protocols/evpn/__init__.py
kathara_lab_checker/checks/protocols/ospf/OSPFInterfaceCheck.py
kathara_lab_checker/checks/protocols/ospf/OSPFNeighborCheck.py
kathara_lab_checker/checks/protocols/ospf/OSPFRoutesCheck.py
kathara_lab_checker/checks/protocols/ospf/__init__.py
kathara_lab_checker-0.1.11.dist-info/licenses/LICENSE
kathara_lab_checker-0.1.11.dist-info/METADATA
kathara_lab_checker-0.1.11.dist-info/WHEEL
kathara_lab_checker-0.1.11.dist-info/entry_points.txt
kathara_lab_checker-0.1.11.dist-info/top_level.txt
kathara_lab_checker-0.1.11.dist-info/RECORD
