Metadata-Version: 2.4
Name: kathara_lab_checker
Version: 0.1.11
Summary: Tool to automatically check Kathará network scenarios based on a configuration file.
Author-email: Kathara Framework <contact@kathara.org>
Maintainer-email: Tommaso Caiazzi <contact@kathara.org>, Lorenzo Ariemma <contact@kathara.org>
License:                     GNU GENERAL PUBLIC LICENSE
Project-URL: Bug Reports, https://github.com/KatharaFramework/kathara-lab-checker/issues
Project-URL: Source, https://github.com/KatharaFramework/kathara-lab-checker
Keywords: Kathara,NETWORK-EMULATION
Classifier: Development Status :: 5 - Production/Stable
Classifier: Intended Audience :: Science/Research
Classifier: Intended Audience :: Education
Classifier: Intended Audience :: Telecommunications Industry
Classifier: Topic :: Software Development :: Build Tools
Classifier: License :: OSI Approved :: GNU General Public License v3 or later (GPLv3+)
Classifier: Programming Language :: Python :: 3.11
Requires-Python: >=3.11
License-File: LICENSE
Requires-Dist: kathara>=3.7.7
Requires-Dist: jc>=1.24.0
Requires-Dist: openpyxl>=3.1.2
Requires-Dist: tqdm>=4
Requires-Dist: coloredlogs~=15.0.1
Dynamic: license-file
